ragnosis/__init__.py
ragnosis/aux.py
ragnosis/grounding.py
ragnosis/models.py
ragnosis-0.1.5.dist-info/LICENSE
ragnosis-0.1.5.dist-info/METADATA
ragnosis-0.1.5.dist-info/WHEEL
ragnosis-0.1.5.dist-info/entry_points.txt
ragnosis-0.1.5.dist-info/top_level.txt
ragnosis-0.1.5.dist-info/RECORD
