Metadata-Version: 2.1
Name: ragnosis
Version: 0.1.5
Summary: LLM-retrieval based knowledge grounding
Author-email: gkreder <gk@reder.io>
License: MIT License
Project-URL: Homepage, https://github.com/gkreder/ragnosis
Project-URL: Source Code, https://github.com/gkreder/ragnosis
Project-URL: Bug Tracker, https://github.com/gkreder/ragnosis/issues
Classifier: Programming Language :: Python :: 3
Classifier: License :: OSI Approved :: MIT License
Classifier: Operating System :: OS Independent
Requires-Python: <3.13,>=3.8
License-File: LICENSE
Requires-Dist: python-dotenv==1.0.1
Requires-Dist: openai<2,>=1.48.0
Requires-Dist: langchain<0.4,>=0.3.0
Requires-Dist: streamlit==1.37
Requires-Dist: beautifulsoup4<5,>=4.12.3
Requires-Dist: rdflib==7.0.0
Requires-Dist: langchain-community<0.4,>=0.3.0
Requires-Dist: langchain-ollama<0.3,>=0.2.0
Requires-Dist: fastembed<0.4,>=0.3.6
Requires-Dist: faiss-cpu<2,>=1.8.0.post1
Requires-Dist: langchain-openai<0.3,>=0.2.0
Requires-Dist: pymupdf<2,>=1.24.10
Requires-Dist: sentence-transformers<4,>=3.1.1
Requires-Dist: langchain-huggingface<0.2,>=0.1.0
Requires-Dist: langgraph<0.3,>=0.2.34
Requires-Dist: markdown<4,>=3.7
Requires-Dist: pdfkit<2,>=1.0.0
